cnextb/__init__.py
cnextb/connection.py
cnextb/run.py
cnextb/smoke.py
cnextb/connection_specific/__init__.py
cnextb/connection_specific/connection_Serial.py
cnextb/connection_specific/serial/__init__.py
cnextb/connection_specific/serial/rfc2217.py
cnextb/connection_specific/serial/rs485.py
cnextb/connection_specific/serial/serialcli.py
cnextb/connection_specific/serial/serialjava.py
cnextb/connection_specific/serial/serialposix.py
cnextb/connection_specific/serial/serialutil.py
cnextb/connection_specific/serial/serialwin32.py
cnextb/connection_specific/serial/win32.py
cnextb/connection_specific/serial/threaded/__init__.py
cnextb/connection_specific/serial/tools/__init__.py
cnextb/connection_specific/serial/tools/hexlify_codec.py
cnextb/connection_specific/serial/tools/list_ports.py
cnextb/connection_specific/serial/tools/list_ports_common.py
cnextb/connection_specific/serial/tools/list_ports_linux.py
cnextb/connection_specific/serial/tools/list_ports_osx.py
cnextb/connection_specific/serial/tools/list_ports_posix.py
cnextb/connection_specific/serial/tools/list_ports_windows.py
cnextb/connection_specific/serial/tools/miniterm.py
cnextb/connection_specific/serial/urlhandler/__init__.py
cnextb/connection_specific/serial/urlhandler/protocol_alt.py
cnextb/connection_specific/serial/urlhandler/protocol_hwgrep.py
cnextb/connection_specific/serial/urlhandler/protocol_loop.py
cnextb/connection_specific/serial/urlhandler/protocol_rfc2217.py
cnextb/connection_specific/serial/urlhandler/protocol_socket.py
cnextb/connection_specific/serial/urlhandler/protocol_spy.py
cnextb/debug/__init__.py
cnextb/debug/terminal.py
cnextb/device/__init__.py
cnextb/device/device.py
cnextb/device/scanDevices.py
cnextb-1.0.4.dist-info/METADATA
cnextb-1.0.4.dist-info/WHEEL
cnextb-1.0.4.dist-info/top_level.txt
cnextb-1.0.4.dist-info/RECORD
