Metadata-Version: 2.1
Name: cnextb
Version: 1.0.4
Summary: test board developped by CNEXLABS
Home-page: UNKNOWN
License: UNKNOWN
Platform: UNKNOWN
Requires-Python: >=3
